aionix/__init__.py
aionix-0.0.1.dev0.dist-info/METADATA
aionix-0.0.1.dev0.dist-info/WHEEL
aionix-0.0.1.dev0.dist-info/licenses/LICENSE
aionix-0.0.1.dev0.dist-info/RECORD
