Metadata-Version: 2.4
Name: aionix
Version: 0.0.1.dev0
Summary: 
License-Expression: MIT
License-File: LICENSE
Author: Dmitry Ryumin
Author-email: neweraairesearch@gmail.com
Requires-Python: >=3.12.10,<3.13
Classifier: Programming Language :: Python :: 3
Requires-Dist: torch (>=2.9.1,<3.0.0)
Requires-Dist: torchaudio (>=2.9.1,<3.0.0)
Requires-Dist: torchvision (>=0.24.1,<0.25.0)
Project-URL: Documentation, https://github.com/DmitryRyumin/aionix
Project-URL: Homepage, https://github.com/DmitryRyumin/aionix
Project-URL: Repository, https://github.com/DmitryRyumin/aionix
